{"@context":{"reporter":"http://github.com/w3c/wai-wcag-em-report-tool/","wcagem":"http://www.w3.org/TR/WCAG-EM/#","Evaluation":"wcagem:procedure","defineScope":"wcagem:step1","scope":"wcagem:step1a","step1b":{"@id":"wcagem:step1b","@type":"@id"},"conformanceTarget":"step1b","accessibilitySupportBaseline":"wcagem:step1c","additionalEvaluationRequirements":"wcagem:step1d","exploreTarget":"wcagem:step2","essentialFunctionality":"wcagem:step2b","pageTypeVariety":"wcagem:step2c","technologiesReliedUpon":"wcagem:step2d","selectSample":"wcagem:step3","structuredSample":"wcagem:step3a","randomSample":"wcagem:step3b","Website":"wcagem:website","Webpage":"wcagem:webpage","auditSample":"wcagem:step4","reportFindings":"wcagem:step5","documentSteps":"wcagem:step5a","commissioner":"wcagem:commissioner","evaluator":"wcagem:evaluator","evaluationSpecifics":"wcagem:step5b","WCAG":"http://www.w3.org/TR/WCAG/#","WCAG20":"http://www.w3.org/TR/WCAG20/#","WCAG21":"http://www.w3.org/TR/WCAG21/#","WAI":"http://www.w3.org/WAI/","A":"WAI:WCAG2A-Conformance","AA":"WAI:WCAG2AA-Conformance","AAA":"WAI:WCAG2AAA-Conformance","wcagVersion":"WAI:standards-guidelines/wcag/#versions","reportToolVersion":"wcagem:reportToolVersion","earl":"http://www.w3.org/ns/earl#","Assertion":"earl:Assertion","TestMode":"earl:TestMode","TestCriterion":"earl:TestCriterion","TestCase":"earl:TestCase","TestRequirement":"earl:TestRequirement","TestSubject":"earl:TestSubject","TestResult":"earl:TestResult","OutcomeValue":"earl:OutcomeValue","Pass":"earl:Pass","Fail":"earl:Fail","CannotTell":"earl:CannotTell","NotApplicable":"earl:NotApplicable","NotTested":"earl:NotTested","assertedBy":"earl:assertedBy","mode":"earl:mode","result":"earl:result","subject":"earl:subject","test":"earl:test","outcome":"earl:outcome","dcterms":"http://purl.org/dc/terms/","title":"dcterms:title","description":"dcterms:description","summary":"dcterms:summary","date":"dcterms:date","hasPart":"dcterms:hasPart","isPartOf":"dcterms:isPartOf","id":"@id","type":"@type","language":"@language"},"language":"en","type":"Evaluation","reportToolVersion":"3.0.3","defineScope":{"id":"_:defineScope","scope":{"description":"https://nav.no/*/minside/varslinger","title":"nav.no – Min side – Varslinger"},"conformanceTarget":"AA","accessibilitySupportBaseline":"","additionalEvaluationRequirements":"","wcagVersion":"2.1"},"exploreTarget":{"id":"_:exploreTarget","essentialFunctionality":"","pageTypeVariety":"","technologiesReliedUpon":["HTML","CSS","WAI-ARIA","JavaScript","SVG"]},"selectSample":{"id":"_:selectSample","structuredSample":[],"randomSample":[]},"auditSample":[{"type":"Assertion","date":"2022-12-05T12:43:47.432Z","mode":{"type":"TestMode","@value":"earl:manual"},"result":{"type":"TestResult","date":"2022-12-05T12:48:28.001Z","description":"svg-ikoner har ikke alt-tekst og er ikke merket med role=\"presentation\"","outcome":{"id":"earl:failed","type":["OutcomeValue","Fail"],"title":"Failed"}},"subject":{"id":"_:subject_1","type":["TestSubject","Website"],"date":"2022-12-05T12:43:33.520Z","description":"https://nav.no/*/minside/varslinger","title":"nav.no – Min side – Varslinger"},"test":{"id":"WCAG21:non-text-content","type":["TestCriterion","TestRequirement"],"date":"2022-12-05T12:43:33.520Z"}},{"type":"Assertion","date":"2022-12-05T12:43:47.432Z","mode":{"type":"TestMode","@value":"earl:manual"},"result":{"type":"TestResult","date":"2022-12-05T12:49:36.369Z","description":"","outcome":{"id":"earl:inapplicable","type":["OutcomeValue","NotApplicable"],"title":"Not present"}},"subject":{"id":"_:subject_1","type":["TestSubject","Website"],"date":"2022-12-05T12:43:33.520Z","description":"https://nav.no/*/minside/varslinger","title":"nav.no – Min side – Varslinger"},"test":{"id":"WCAG21:audio-only-and-video-only-prerecorded","type":["TestCriterion","TestRequirement"],"date":"2022-12-05T12:43:33.520Z"}},{"type":"Assertion","date":"2022-12-05T12:43:47.433Z","mode":{"type":"TestMode","@value":"earl:manual"},"result":{"type":"TestResult","date":"2022-12-05T12:49:39.400Z","description":"","outcome":{"id":"earl:inapplicable","type":["OutcomeValue","NotApplicable"],"title":"Not present"}},"subject":{"id":"_:subject_1","type":["TestSubject","Website"],"date":"2022-12-05T12:43:33.520Z","description":"https://nav.no/*/minside/varslinger","title":"nav.no – Min side – Varslinger"},"test":{"id":"WCAG21:captions-prerecorded","type":["TestCriterion","TestRequirement"],"date":"2022-12-05T12:43:33.520Z"}},{"type":"Assertion","date":"2022-12-05T12:43:47.433Z","mode":{"type":"TestMode","@value":"earl:manual"},"result":{"type":"TestResult","date":"2022-12-05T12:49:41.903Z","description":"","outcome":{"id":"earl:inapplicable","type":["OutcomeValue","NotApplicable"],"title":"Not present"}},"subject":{"id":"_:subject_1","type":["TestSubject","Website"],"date":"2022-12-05T12:43:33.520Z","description":"https://nav.no/*/minside/varslinger","title":"nav.no – Min side – Varslinger"},"test":{"id":"WCAG21:audio-description-or-media-alternative-prerecorded","type":["TestCriterion","TestRequirement"],"date":"2022-12-05T12:43:33.520Z"}},{"type":"Assertion","date":"2022-12-05T12:43:47.433Z","mode":{"type":"TestMode","@value":"earl:manual"},"result":{"type":"TestResult","date":"2022-12-05T12:49:47.046Z","description":"","outcome":{"id":"earl:inapplicable","type":["OutcomeValue","NotApplicable"],"title":"Not present"}},"subject":{"id":"_:subject_1","type":["TestSubject","Website"],"date":"2022-12-05T12:43:33.520Z","description":"https://nav.no/*/minside/varslinger","title":"nav.no – Min side – Varslinger"},"test":{"id":"WCAG21:captions-live","type":["TestCriterion","TestRequirement"],"date":"2022-12-05T12:43:33.520Z"}},{"type":"Assertion","date":"2022-12-05T12:43:47.433Z","mode":{"type":"TestMode","@value":"earl:manual"},"result":{"type":"TestResult","date":"2022-12-05T12:49:49.883Z","description":"","outcome":{"id":"earl:inapplicable","type":["OutcomeValue","NotApplicable"],"title":"Not present"}},"subject":{"id":"_:subject_1","type":["TestSubject","Website"],"date":"2022-12-05T12:43:33.520Z","description":"https://nav.no/*/minside/varslinger","title":"nav.no – Min side – Varslinger"},"test":{"id":"WCAG21:audio-description-prerecorded","type":["TestCriterion","TestRequirement"],"date":"2022-12-05T12:43:33.520Z"}},{"type":"Assertion","date":"2022-12-05T12:43:47.433Z","mode":{"type":"TestMode","@value":"earl:manual"},"result":{"type":"TestResult","date":"2022-12-05T12:50:21.063Z","description":"Duplikat main-tag\nFeil i header-nivåer","outcome":{"id":"earl:failed","type":["OutcomeValue","Fail"],"title":"Failed"}},"subject":{"id":"_:subject_1","type":["TestSubject","Website"],"date":"2022-12-05T12:43:33.520Z","description":"https://nav.no/*/minside/varslinger","title":"nav.no – Min side – Varslinger"},"test":{"id":"WCAG21:info-and-relationships","type":["TestCriterion","TestRequirement"],"date":"2022-12-05T12:43:33.520Z"}},{"type":"Assertion","date":"2022-12-05T12:43:47.433Z","mode":{"type":"TestMode","@value":"earl:manual"},"result":{"type":"TestResult","date":"2022-12-05T12:51:25.709Z","description":"Umulig å avgjøre typen varsel programatisk","outcome":{"id":"earl:failed","type":["OutcomeValue","Fail"],"title":"Failed"}},"subject":{"id":"_:subject_1","type":["TestSubject","Website"],"date":"2022-12-05T12:43:33.520Z","description":"https://nav.no/*/minside/varslinger","title":"nav.no – Min side – Varslinger"},"test":{"id":"WCAG21:meaningful-sequence","type":["TestCriterion","TestRequirement"],"date":"2022-12-05T12:43:33.520Z"}},{"type":"Assertion","date":"2022-12-05T12:43:47.433Z","mode":{"type":"TestMode","@value":"earl:manual"},"result":{"type":"TestResult","date":"2022-12-05T12:50:28.281Z","description":"","outcome":{"id":"earl:passed","type":["OutcomeValue","Pass"],"title":"Passed"}},"subject":{"id":"_:subject_1","type":["TestSubject","Website"],"date":"2022-12-05T12:43:33.520Z","description":"https://nav.no/*/minside/varslinger","title":"nav.no – Min side – Varslinger"},"test":{"id":"WCAG21:sensory-characteristics","type":["TestCriterion","TestRequirement"],"date":"2022-12-05T12:43:33.520Z"}},{"type":"Assertion","date":"2022-12-05T12:43:47.433Z","mode":{"type":"TestMode","@value":"earl:manual"},"result":{"type":"TestResult","date":"2022-12-05T12:51:27.871Z","description":"","outcome":{"id":"earl:passed","type":["OutcomeValue","Pass"],"title":"Passed"}},"subject":{"id":"_:subject_1","type":["TestSubject","Website"],"date":"2022-12-05T12:43:33.520Z","description":"https://nav.no/*/minside/varslinger","title":"nav.no – Min side – Varslinger"},"test":{"id":"WCAG21:orientation","type":["TestCriterion","TestRequirement"],"date":"2022-12-05T12:43:33.520Z"}},{"type":"Assertion","date":"2022-12-05T12:43:47.433Z","mode":{"type":"TestMode","@value":"earl:manual"},"result":{"type":"TestResult","date":"2022-12-05T12:51:36.416Z","description":"","outcome":{"id":"earl:passed","type":["OutcomeValue","Pass"],"title":"Passed"}},"subject":{"id":"_:subject_1","type":["TestSubject","Website"],"date":"2022-12-05T12:43:33.520Z","description":"https://nav.no/*/minside/varslinger","title":"nav.no – Min side – Varslinger"},"test":{"id":"WCAG21:identify-input-purpose","type":["TestCriterion","TestRequirement"],"date":"2022-12-05T12:43:33.520Z"}},{"type":"Assertion","date":"2022-12-05T12:43:47.433Z","mode":{"type":"TestMode","@value":"earl:manual"},"result":{"type":"TestResult","date":"2022-12-05T12:51:40.322Z","description":"","outcome":{"id":"earl:passed","type":["OutcomeValue","Pass"],"title":"Passed"}},"subject":{"id":"_:subject_1","type":["TestSubject","Website"],"date":"2022-12-05T12:43:33.520Z","description":"https://nav.no/*/minside/varslinger","title":"nav.no – Min side – Varslinger"},"test":{"id":"WCAG21:use-of-color","type":["TestCriterion","TestRequirement"],"date":"2022-12-05T12:43:33.520Z"}},{"type":"Assertion","date":"2022-12-05T12:43:47.433Z","mode":{"type":"TestMode","@value":"earl:manual"},"result":{"type":"TestResult","date":"2022-12-05T12:51:45.383Z","description":"","outcome":{"id":"earl:inapplicable","type":["OutcomeValue","NotApplicable"],"title":"Not present"}},"subject":{"id":"_:subject_1","type":["TestSubject","Website"],"date":"2022-12-05T12:43:33.520Z","description":"https://nav.no/*/minside/varslinger","title":"nav.no – Min side – Varslinger"},"test":{"id":"WCAG21:audio-control","type":["TestCriterion","TestRequirement"],"date":"2022-12-05T12:43:33.520Z"}},{"type":"Assertion","date":"2022-12-05T12:43:47.433Z","mode":{"type":"TestMode","@value":"earl:manual"},"result":{"type":"TestResult","date":"2022-12-05T12:51:53.185Z","description":"","outcome":{"id":"earl:passed","type":["OutcomeValue","Pass"],"title":"Passed"}},"subject":{"id":"_:subject_1","type":["TestSubject","Website"],"date":"2022-12-05T12:43:33.520Z","description":"https://nav.no/*/minside/varslinger","title":"nav.no – Min side – Varslinger"},"test":{"id":"WCAG21:contrast-minimum","type":["TestCriterion","TestRequirement"],"date":"2022-12-05T12:43:33.520Z"}},{"type":"Assertion","date":"2022-12-05T12:43:47.434Z","mode":{"type":"TestMode","@value":"earl:manual"},"result":{"type":"TestResult","date":"2022-12-05T13:04:32.000Z","description":"Liten skjerm: reflow for lange ord fungerer ikke","outcome":{"id":"earl:failed","type":["OutcomeValue","Fail"],"title":"Failed"}},"subject":{"id":"_:subject_1","type":["TestSubject","Website"],"date":"2022-12-05T12:43:33.520Z","description":"https://nav.no/*/minside/varslinger","title":"nav.no – Min side – Varslinger"},"test":{"id":"WCAG21:resize-text","type":["TestCriterion","TestRequirement"],"date":"2022-12-05T12:43:33.520Z"}},{"type":"Assertion","date":"2022-12-05T12:43:47.434Z","mode":{"type":"TestMode","@value":"earl:manual"},"result":{"type":"TestResult","date":"2022-12-05T12:52:04.489Z","description":"","outcome":{"id":"earl:inapplicable","type":["OutcomeValue","NotApplicable"],"title":"Not present"}},"subject":{"id":"_:subject_1","type":["TestSubject","Website"],"date":"2022-12-05T12:43:33.520Z","description":"https://nav.no/*/minside/varslinger","title":"nav.no – Min side – Varslinger"},"test":{"id":"WCAG21:images-of-text","type":["TestCriterion","TestRequirement"],"date":"2022-12-05T12:43:33.520Z"}},{"type":"Assertion","date":"2022-12-05T12:43:47.434Z","mode":{"type":"TestMode","@value":"earl:manual"},"result":{"type":"TestResult","date":"2022-12-05T12:52:14.720Z","description":"","outcome":{"id":"earl:passed","type":["OutcomeValue","Pass"],"title":"Passed"}},"subject":{"id":"_:subject_1","type":["TestSubject","Website"],"date":"2022-12-05T12:43:33.520Z","description":"https://nav.no/*/minside/varslinger","title":"nav.no – Min side – Varslinger"},"test":{"id":"WCAG21:reflow","type":["TestCriterion","TestRequirement"],"date":"2022-12-05T12:43:33.520Z"}},{"type":"Assertion","date":"2022-12-05T12:43:47.434Z","mode":{"type":"TestMode","@value":"earl:manual"},"result":{"type":"TestResult","date":"2022-12-05T12:52:19.377Z","description":"","outcome":{"id":"earl:passed","type":["OutcomeValue","Pass"],"title":"Passed"}},"subject":{"id":"_:subject_1","type":["TestSubject","Website"],"date":"2022-12-05T12:43:33.520Z","description":"https://nav.no/*/minside/varslinger","title":"nav.no – Min side – Varslinger"},"test":{"id":"WCAG21:non-text-contrast","type":["TestCriterion","TestRequirement"],"date":"2022-12-05T12:43:33.520Z"}},{"type":"Assertion","date":"2022-12-05T12:43:47.434Z","mode":{"type":"TestMode","@value":"earl:manual"},"result":{"type":"TestResult","date":"2022-12-05T13:03:34.510Z","description":"","outcome":{"id":"earl:passed","type":["OutcomeValue","Pass"],"title":"Passed"}},"subject":{"id":"_:subject_1","type":["TestSubject","Website"],"date":"2022-12-05T12:43:33.520Z","description":"https://nav.no/*/minside/varslinger","title":"nav.no – Min side – Varslinger"},"test":{"id":"WCAG21:text-spacing","type":["TestCriterion","TestRequirement"],"date":"2022-12-05T12:43:33.520Z"}},{"type":"Assertion","date":"2022-12-05T12:43:47.434Z","mode":{"type":"TestMode","@value":"earl:manual"},"result":{"type":"TestResult","date":"2022-12-05T13:03:44.311Z","description":"","outcome":{"id":"earl:inapplicable","type":["OutcomeValue","NotApplicable"],"title":"Not present"}},"subject":{"id":"_:subject_1","type":["TestSubject","Website"],"date":"2022-12-05T12:43:33.520Z","description":"https://nav.no/*/minside/varslinger","title":"nav.no – Min side – Varslinger"},"test":{"id":"WCAG21:content-on-hover-or-focus","type":["TestCriterion","TestRequirement"],"date":"2022-12-05T12:43:33.520Z"}},{"type":"Assertion","date":"2022-12-05T12:43:47.434Z","mode":{"type":"TestMode","@value":"earl:manual"},"result":{"type":"TestResult","date":"2022-12-05T13:04:49.890Z","description":"","outcome":{"id":"earl:passed","type":["OutcomeValue","Pass"],"title":"Passed"}},"subject":{"id":"_:subject_1","type":["TestSubject","Website"],"date":"2022-12-05T12:43:33.520Z","description":"https://nav.no/*/minside/varslinger","title":"nav.no – Min side – Varslinger"},"test":{"id":"WCAG21:keyboard","type":["TestCriterion","TestRequirement"],"date":"2022-12-05T12:43:33.521Z"}},{"type":"Assertion","date":"2022-12-05T12:43:47.434Z","mode":{"type":"TestMode","@value":"earl:manual"},"result":{"type":"TestResult","date":"2022-12-05T13:04:52.928Z","description":"","outcome":{"id":"earl:passed","type":["OutcomeValue","Pass"],"title":"Passed"}},"subject":{"id":"_:subject_1","type":["TestSubject","Website"],"date":"2022-12-05T12:43:33.520Z","description":"https://nav.no/*/minside/varslinger","title":"nav.no – Min side – Varslinger"},"test":{"id":"WCAG21:no-keyboard-trap","type":["TestCriterion","TestRequirement"],"date":"2022-12-05T12:43:33.521Z"}},{"type":"Assertion","date":"2022-12-05T12:43:47.434Z","mode":{"type":"TestMode","@value":"earl:manual"},"result":{"type":"TestResult","date":"2022-12-05T13:04:58.359Z","description":"","outcome":{"id":"earl:inapplicable","type":["OutcomeValue","NotApplicable"],"title":"Not present"}},"subject":{"id":"_:subject_1","type":["TestSubject","Website"],"date":"2022-12-05T12:43:33.520Z","description":"https://nav.no/*/minside/varslinger","title":"nav.no – Min side – Varslinger"},"test":{"id":"WCAG21:character-key-shortcuts","type":["TestCriterion","TestRequirement"],"date":"2022-12-05T12:43:33.521Z"}},{"type":"Assertion","date":"2022-12-05T12:43:47.434Z","mode":{"type":"TestMode","@value":"earl:manual"},"result":{"type":"TestResult","date":"2022-12-05T13:05:02.160Z","description":"","outcome":{"id":"earl:inapplicable","type":["OutcomeValue","NotApplicable"],"title":"Not present"}},"subject":{"id":"_:subject_1","type":["TestSubject","Website"],"date":"2022-12-05T12:43:33.520Z","description":"https://nav.no/*/minside/varslinger","title":"nav.no – Min side – Varslinger"},"test":{"id":"WCAG21:timing-adjustable","type":["TestCriterion","TestRequirement"],"date":"2022-12-05T12:43:33.521Z"}},{"type":"Assertion","date":"2022-12-05T12:43:47.434Z","mode":{"type":"TestMode","@value":"earl:manual"},"result":{"type":"TestResult","date":"2022-12-05T13:05:04.693Z","description":"","outcome":{"id":"earl:inapplicable","type":["OutcomeValue","NotApplicable"],"title":"Not present"}},"subject":{"id":"_:subject_1","type":["TestSubject","Website"],"date":"2022-12-05T12:43:33.520Z","description":"https://nav.no/*/minside/varslinger","title":"nav.no – Min side – Varslinger"},"test":{"id":"WCAG21:pause-stop-hide","type":["TestCriterion","TestRequirement"],"date":"2022-12-05T12:43:33.521Z"}},{"type":"Assertion","date":"2022-12-05T12:43:47.434Z","mode":{"type":"TestMode","@value":"earl:manual"},"result":{"type":"TestResult","date":"2022-12-05T13:05:09.396Z","description":"","outcome":{"id":"earl:passed","type":["OutcomeValue","Pass"],"title":"Passed"}},"subject":{"id":"_:subject_1","type":["TestSubject","Website"],"date":"2022-12-05T12:43:33.520Z","description":"https://nav.no/*/minside/varslinger","title":"nav.no – Min side – Varslinger"},"test":{"id":"WCAG21:three-flashes-or-below-threshold","type":["TestCriterion","TestRequirement"],"date":"2022-12-05T12:43:33.521Z"}},{"type":"Assertion","date":"2022-12-05T12:43:47.434Z","mode":{"type":"TestMode","@value":"earl:manual"},"result":{"type":"TestResult","date":"2022-12-05T13:05:14.293Z","description":"","outcome":{"id":"earl:inapplicable","type":["OutcomeValue","NotApplicable"],"title":"Not present"}},"subject":{"id":"_:subject_1","type":["TestSubject","Website"],"date":"2022-12-05T12:43:33.520Z","description":"https://nav.no/*/minside/varslinger","title":"nav.no – Min side – Varslinger"},"test":{"id":"WCAG21:bypass-blocks","type":["TestCriterion","TestRequirement"],"date":"2022-12-05T12:43:33.521Z"}},{"type":"Assertion","date":"2022-12-05T12:43:47.434Z","mode":{"type":"TestMode","@value":"earl:manual"},"result":{"type":"TestResult","date":"2022-12-05T13:05:39.267Z","description":"title-tag er ikke presist nok","outcome":{"id":"earl:failed","type":["OutcomeValue","Fail"],"title":"Failed"}},"subject":{"id":"_:subject_1","type":["TestSubject","Website"],"date":"2022-12-05T12:43:33.520Z","description":"https://nav.no/*/minside/varslinger","title":"nav.no – Min side – Varslinger"},"test":{"id":"WCAG21:page-titled","type":["TestCriterion","TestRequirement"],"date":"2022-12-05T12:43:33.521Z"}},{"type":"Assertion","date":"2022-12-05T12:43:47.434Z","mode":{"type":"TestMode","@value":"earl:manual"},"result":{"type":"TestResult","date":"2022-12-05T13:05:40.611Z","description":"","outcome":{"id":"earl:passed","type":["OutcomeValue","Pass"],"title":"Passed"}},"subject":{"id":"_:subject_1","type":["TestSubject","Website"],"date":"2022-12-05T12:43:33.520Z","description":"https://nav.no/*/minside/varslinger","title":"nav.no – Min side – Varslinger"},"test":{"id":"WCAG21:focus-order","type":["TestCriterion","TestRequirement"],"date":"2022-12-05T12:43:33.521Z"}},{"type":"Assertion","date":"2022-12-05T12:43:47.434Z","mode":{"type":"TestMode","@value":"earl:manual"},"result":{"type":"TestResult","date":"2022-12-05T13:05:44.843Z","description":"","outcome":{"id":"earl:passed","type":["OutcomeValue","Pass"],"title":"Passed"}},"subject":{"id":"_:subject_1","type":["TestSubject","Website"],"date":"2022-12-05T12:43:33.520Z","description":"https://nav.no/*/minside/varslinger","title":"nav.no – Min side – Varslinger"},"test":{"id":"WCAG21:link-purpose-in-context","type":["TestCriterion","TestRequirement"],"date":"2022-12-05T12:43:33.521Z"}},{"type":"Assertion","date":"2022-12-05T12:43:47.434Z","mode":{"type":"TestMode","@value":"earl:manual"},"result":{"type":"TestResult","date":"2022-12-05T13:05:55.943Z","description":"","outcome":{"id":"earl:passed","type":["OutcomeValue","Pass"],"title":"Passed"}},"subject":{"id":"_:subject_1","type":["TestSubject","Website"],"date":"2022-12-05T12:43:33.520Z","description":"https://nav.no/*/minside/varslinger","title":"nav.no – Min side – Varslinger"},"test":{"id":"WCAG21:multiple-ways","type":["TestCriterion","TestRequirement"],"date":"2022-12-05T12:43:33.521Z"}},{"type":"Assertion","date":"2022-12-05T12:43:47.434Z","mode":{"type":"TestMode","@value":"earl:manual"},"result":{"type":"TestResult","date":"2022-12-05T13:06:01.993Z","description":"","outcome":{"id":"earl:passed","type":["OutcomeValue","Pass"],"title":"Passed"}},"subject":{"id":"_:subject_1","type":["TestSubject","Website"],"date":"2022-12-05T12:43:33.520Z","description":"https://nav.no/*/minside/varslinger","title":"nav.no – Min side – Varslinger"},"test":{"id":"WCAG21:headings-and-labels","type":["TestCriterion","TestRequirement"],"date":"2022-12-05T12:43:33.521Z"}},{"type":"Assertion","date":"2022-12-05T12:43:47.434Z","mode":{"type":"TestMode","@value":"earl:manual"},"result":{"type":"TestResult","date":"2022-12-05T13:06:05.513Z","description":"","outcome":{"id":"earl:passed","type":["OutcomeValue","Pass"],"title":"Passed"}},"subject":{"id":"_:subject_1","type":["TestSubject","Website"],"date":"2022-12-05T12:43:33.520Z","description":"https://nav.no/*/minside/varslinger","title":"nav.no – Min side – Varslinger"},"test":{"id":"WCAG21:focus-visible","type":["TestCriterion","TestRequirement"],"date":"2022-12-05T12:43:33.521Z"}},{"type":"Assertion","date":"2022-12-05T12:43:47.434Z","mode":{"type":"TestMode","@value":"earl:manual"},"result":{"type":"TestResult","date":"2022-12-05T13:06:11.880Z","description":"","outcome":{"id":"earl:inapplicable","type":["OutcomeValue","NotApplicable"],"title":"Not present"}},"subject":{"id":"_:subject_1","type":["TestSubject","Website"],"date":"2022-12-05T12:43:33.520Z","description":"https://nav.no/*/minside/varslinger","title":"nav.no – Min side – Varslinger"},"test":{"id":"WCAG21:pointer-gestures","type":["TestCriterion","TestRequirement"],"date":"2022-12-05T12:43:33.521Z"}},{"type":"Assertion","date":"2022-12-05T12:43:47.434Z","mode":{"type":"TestMode","@value":"earl:manual"},"result":{"type":"TestResult","date":"2022-12-05T13:06:34.761Z","description":"","outcome":{"id":"earl:inapplicable","type":["OutcomeValue","NotApplicable"],"title":"Not present"}},"subject":{"id":"_:subject_1","type":["TestSubject","Website"],"date":"2022-12-05T12:43:33.520Z","description":"https://nav.no/*/minside/varslinger","title":"nav.no – Min side – Varslinger"},"test":{"id":"WCAG21:pointer-cancellation","type":["TestCriterion","TestRequirement"],"date":"2022-12-05T12:43:33.521Z"}},{"type":"Assertion","date":"2022-12-05T12:43:47.434Z","mode":{"type":"TestMode","@value":"earl:manual"},"result":{"type":"TestResult","date":"2022-12-05T13:06:40.128Z","description":"","outcome":{"id":"earl:inapplicable","type":["OutcomeValue","NotApplicable"],"title":"Not present"}},"subject":{"id":"_:subject_1","type":["TestSubject","Website"],"date":"2022-12-05T12:43:33.520Z","description":"https://nav.no/*/minside/varslinger","title":"nav.no – Min side – Varslinger"},"test":{"id":"WCAG21:label-in-name","type":["TestCriterion","TestRequirement"],"date":"2022-12-05T12:43:33.521Z"}},{"type":"Assertion","date":"2022-12-05T12:43:47.434Z","mode":{"type":"TestMode","@value":"earl:manual"},"result":{"type":"TestResult","date":"2022-12-05T13:06:50.196Z","description":"","outcome":{"id":"earl:inapplicable","type":["OutcomeValue","NotApplicable"],"title":"Not present"}},"subject":{"id":"_:subject_1","type":["TestSubject","Website"],"date":"2022-12-05T12:43:33.520Z","description":"https://nav.no/*/minside/varslinger","title":"nav.no – Min side – Varslinger"},"test":{"id":"WCAG21:motion-actuation","type":["TestCriterion","TestRequirement"],"date":"2022-12-05T12:43:33.521Z"}},{"type":"Assertion","date":"2022-12-05T12:43:47.434Z","mode":{"type":"TestMode","@value":"earl:manual"},"result":{"type":"TestResult","date":"2022-12-05T13:06:57.409Z","description":"","outcome":{"id":"earl:passed","type":["OutcomeValue","Pass"],"title":"Passed"}},"subject":{"id":"_:subject_1","type":["TestSubject","Website"],"date":"2022-12-05T12:43:33.520Z","description":"https://nav.no/*/minside/varslinger","title":"nav.no – Min side – Varslinger"},"test":{"id":"WCAG21:language-of-page","type":["TestCriterion","TestRequirement"],"date":"2022-12-05T12:43:33.521Z"}},{"type":"Assertion","date":"2022-12-05T12:43:47.434Z","mode":{"type":"TestMode","@value":"earl:manual"},"result":{"type":"TestResult","date":"2022-12-05T13:06:59.961Z","description":"","outcome":{"id":"earl:inapplicable","type":["OutcomeValue","NotApplicable"],"title":"Not present"}},"subject":{"id":"_:subject_1","type":["TestSubject","Website"],"date":"2022-12-05T12:43:33.520Z","description":"https://nav.no/*/minside/varslinger","title":"nav.no – Min side – Varslinger"},"test":{"id":"WCAG21:language-of-parts","type":["TestCriterion","TestRequirement"],"date":"2022-12-05T12:43:33.521Z"}},{"type":"Assertion","date":"2022-12-05T12:43:47.434Z","mode":{"type":"TestMode","@value":"earl:manual"},"result":{"type":"TestResult","date":"2022-12-05T13:07:06.198Z","description":"","outcome":{"id":"earl:passed","type":["OutcomeValue","Pass"],"title":"Passed"}},"subject":{"id":"_:subject_1","type":["TestSubject","Website"],"date":"2022-12-05T12:43:33.520Z","description":"https://nav.no/*/minside/varslinger","title":"nav.no – Min side – Varslinger"},"test":{"id":"WCAG21:on-focus","type":["TestCriterion","TestRequirement"],"date":"2022-12-05T12:43:33.521Z"}},{"type":"Assertion","date":"2022-12-05T12:43:47.434Z","mode":{"type":"TestMode","@value":"earl:manual"},"result":{"type":"TestResult","date":"2022-12-05T13:07:09.058Z","description":"","outcome":{"id":"earl:passed","type":["OutcomeValue","Pass"],"title":"Passed"}},"subject":{"id":"_:subject_1","type":["TestSubject","Website"],"date":"2022-12-05T12:43:33.520Z","description":"https://nav.no/*/minside/varslinger","title":"nav.no – Min side – Varslinger"},"test":{"id":"WCAG21:on-input","type":["TestCriterion","TestRequirement"],"date":"2022-12-05T12:43:33.521Z"}},{"type":"Assertion","date":"2022-12-05T12:43:47.435Z","mode":{"type":"TestMode","@value":"earl:manual"},"result":{"type":"TestResult","date":"2022-12-05T13:07:25.443Z","description":"","outcome":{"id":"earl:passed","type":["OutcomeValue","Pass"],"title":"Passed"}},"subject":{"id":"_:subject_1","type":["TestSubject","Website"],"date":"2022-12-05T12:43:33.520Z","description":"https://nav.no/*/minside/varslinger","title":"nav.no – Min side – Varslinger"},"test":{"id":"WCAG21:consistent-navigation","type":["TestCriterion","TestRequirement"],"date":"2022-12-05T12:43:33.521Z"}},{"type":"Assertion","date":"2022-12-05T12:43:47.435Z","mode":{"type":"TestMode","@value":"earl:manual"},"result":{"type":"TestResult","date":"2022-12-05T13:07:29.909Z","description":"","outcome":{"id":"earl:passed","type":["OutcomeValue","Pass"],"title":"Passed"}},"subject":{"id":"_:subject_1","type":["TestSubject","Website"],"date":"2022-12-05T12:43:33.520Z","description":"https://nav.no/*/minside/varslinger","title":"nav.no – Min side – Varslinger"},"test":{"id":"WCAG21:consistent-identification","type":["TestCriterion","TestRequirement"],"date":"2022-12-05T12:43:33.521Z"}},{"type":"Assertion","date":"2022-12-05T12:43:47.435Z","mode":{"type":"TestMode","@value":"earl:manual"},"result":{"type":"TestResult","date":"2022-12-05T13:07:38.581Z","description":"","outcome":{"id":"earl:inapplicable","type":["OutcomeValue","NotApplicable"],"title":"Not present"}},"subject":{"id":"_:subject_1","type":["TestSubject","Website"],"date":"2022-12-05T12:43:33.520Z","description":"https://nav.no/*/minside/varslinger","title":"nav.no – Min side – Varslinger"},"test":{"id":"WCAG21:error-identification","type":["TestCriterion","TestRequirement"],"date":"2022-12-05T12:43:33.521Z"}},{"type":"Assertion","date":"2022-12-05T12:43:47.435Z","mode":{"type":"TestMode","@value":"earl:manual"},"result":{"type":"TestResult","date":"2022-12-05T13:08:09.110Z","description":"","outcome":{"id":"earl:passed","type":["OutcomeValue","Pass"],"title":"Passed"}},"subject":{"id":"_:subject_1","type":["TestSubject","Website"],"date":"2022-12-05T12:43:33.520Z","description":"https://nav.no/*/minside/varslinger","title":"nav.no – Min side – Varslinger"},"test":{"id":"WCAG21:labels-or-instructions","type":["TestCriterion","TestRequirement"],"date":"2022-12-05T12:43:33.521Z"}},{"type":"Assertion","date":"2022-12-05T12:43:47.435Z","mode":{"type":"TestMode","@value":"earl:manual"},"result":{"type":"TestResult","date":"2022-12-05T13:08:12.827Z","description":"","outcome":{"id":"earl:inapplicable","type":["OutcomeValue","NotApplicable"],"title":"Not present"}},"subject":{"id":"_:subject_1","type":["TestSubject","Website"],"date":"2022-12-05T12:43:33.520Z","description":"https://nav.no/*/minside/varslinger","title":"nav.no – Min side – Varslinger"},"test":{"id":"WCAG21:error-suggestion","type":["TestCriterion","TestRequirement"],"date":"2022-12-05T12:43:33.521Z"}},{"type":"Assertion","date":"2022-12-05T12:43:47.435Z","mode":{"type":"TestMode","@value":"earl:manual"},"result":{"type":"TestResult","date":"2022-12-05T13:08:15.347Z","description":"","outcome":{"id":"earl:inapplicable","type":["OutcomeValue","NotApplicable"],"title":"Not present"}},"subject":{"id":"_:subject_1","type":["TestSubject","Website"],"date":"2022-12-05T12:43:33.520Z","description":"https://nav.no/*/minside/varslinger","title":"nav.no – Min side – Varslinger"},"test":{"id":"WCAG21:error-prevention-legal-financial-data","type":["TestCriterion","TestRequirement"],"date":"2022-12-05T12:43:33.521Z"}},{"type":"Assertion","date":"2022-12-05T12:43:47.435Z","mode":{"type":"TestMode","@value":"earl:manual"},"result":{"type":"TestResult","date":"2022-12-05T13:08:20.908Z","description":"","outcome":{"id":"earl:passed","type":["OutcomeValue","Pass"],"title":"Passed"}},"subject":{"id":"_:subject_1","type":["TestSubject","Website"],"date":"2022-12-05T12:43:33.520Z","description":"https://nav.no/*/minside/varslinger","title":"nav.no – Min side – Varslinger"},"test":{"id":"WCAG21:parsing","type":["TestCriterion","TestRequirement"],"date":"2022-12-05T12:43:33.521Z"}},{"type":"Assertion","date":"2022-12-05T12:43:47.435Z","mode":{"type":"TestMode","@value":"earl:manual"},"result":{"type":"TestResult","date":"2022-12-05T13:08:26.592Z","description":"","outcome":{"id":"earl:passed","type":["OutcomeValue","Pass"],"title":"Passed"}},"subject":{"id":"_:subject_1","type":["TestSubject","Website"],"date":"2022-12-05T12:43:33.520Z","description":"https://nav.no/*/minside/varslinger","title":"nav.no – Min side – Varslinger"},"test":{"id":"WCAG21:name-role-value","type":["TestCriterion","TestRequirement"],"date":"2022-12-05T12:43:33.521Z"}},{"type":"Assertion","date":"2022-12-05T12:43:47.435Z","mode":{"type":"TestMode","@value":"earl:manual"},"result":{"type":"TestResult","date":"2022-12-05T13:08:34.745Z","description":"","outcome":{"id":"earl:inapplicable","type":["OutcomeValue","NotApplicable"],"title":"Not present"}},"subject":{"id":"_:subject_1","type":["TestSubject","Website"],"date":"2022-12-05T12:43:33.520Z","description":"https://nav.no/*/minside/varslinger","title":"nav.no – Min side – Varslinger"},"test":{"id":"WCAG21:status-messages","type":["TestCriterion","TestRequirement"],"date":"2022-12-05T12:43:33.521Z"}}],"reportFindings":{"date":{"type":"http://www.w3.org/TR/NOTE-datetime","@value":"Mon Dec 05 2022"},"summary":"Undersiden \"varslinger\" for min side inneholder 5 brudd og 24 passerte wcag kriterier. ","title":"","commissioner":"","evaluator":"Team Min Side","documentSteps":[{"id":"_:about"},{"id":"_:defineScope"},{"id":"_:exploreTarget"},{"id":"_:selectSample"}],"evaluationSpecifics":""}}
